jmock/__init__.py
jmock/aiFunctions.py
jmock-0.0.5.dist-info/METADATA
jmock-0.0.5.dist-info/WHEEL
jmock-0.0.5.dist-info/top_level.txt
jmock-0.0.5.dist-info/RECORD
