Metadata-Version: 2.1
Name: jmock
Version: 0.0.5
Summary: Joe's Synthetic Data Generator
Author: Joepeter Francis
Author-email: jose4.peter42@gmail.com
Keywords: python,jmock,synthetic data generator,mock data
Requires-Dist: langchain
Requires-Dist: python-dotenv
Requires-Dist: langchain-google-genai
